<annotation>
	<folder></folder>
	<filename>IMG_20181228_104356_jpg.rf.9e30c22eb6d2a74a1521585d5b9b020f.jpg</filename>
	<path>IMG_20181228_104356_jpg.rf.9e30c22eb6d2a74a1521585d5b9b020f.jpg</path>
	<source>
		<database>roboflow.ai</database>
	</source>
	<size>
		<width>416</width>
		<height>416</height>
		<depth>3</depth>
	</size>
	<segmented>0</segmented>
	<object>
		<name>ESP8266</name>
		<pose>Unspecified</pose>
		<truncated>0</truncated>
		<difficult>0</difficult>
		<occluded>0</occluded>
		<bndbox>
			<xmin>1</xmin>
			<xmax>148</xmax>
			<ymin>91</ymin>
			<ymax>224</ymax>
		</bndbox>
	</object>
	<object>
		<name>Raspberry_Pi_3</name>
		<pose>Unspecified</pose>
		<truncated>0</truncated>
		<difficult>0</difficult>
		<occluded>0</occluded>
		<bndbox>
			<xmin>98</xmin>
			<xmax>330</xmax>
			<ymin>1</ymin>
			<ymax>206</ymax>
		</bndbox>
	</object>
	<object>
		<name>Arduino_Nano</name>
		<pose>Unspecified</pose>
		<truncated>0</truncated>
		<difficult>0</difficult>
		<occluded>0</occluded>
		<bndbox>
			<xmin>320</xmin>
			<xmax>389</xmax>
			<ymin>125</ymin>
			<ymax>214</ymax>
		</bndbox>
	</object>
</annotation>
