<annotation>
	<folder></folder>
	<filename>IMG_20190104_164615_jpg.rf.6644bd61e430b1327a3554f7bb61921f.jpg</filename>
	<path>IMG_20190104_164615_jpg.rf.6644bd61e430b1327a3554f7bb61921f.jpg</path>
	<source>
		<database>roboflow.ai</database>
	</source>
	<size>
		<width>416</width>
		<height>416</height>
		<depth>3</depth>
	</size>
	<segmented>0</segmented>
	<object>
		<name>Raspberry_Pi_3</name>
		<pose>Unspecified</pose>
		<truncated>0</truncated>
		<difficult>0</difficult>
		<occluded>0</occluded>
		<bndbox>
			<xmin>76</xmin>
			<xmax>240</xmax>
			<ymin>202</ymin>
			<ymax>356</ymax>
		</bndbox>
	</object>
</annotation>
